git_fork_recon/__init__.py
git_fork_recon/cli.py
git_fork_recon/config.py
git_fork_recon/main.py
git_fork_recon/git/repo.py
git_fork_recon/github/api.py
git_fork_recon/llm/client.py
git_fork_recon/report/generator.py
git_fork_recon/report/pandoc.py
git_fork_recon/report/templates/master.md.jinja
git_fork_recon/report/templates/report.md.jinja
git_fork_recon_server/__init__.py
git_fork_recon_server/analysis.py
git_fork_recon_server/app.py
git_fork_recon_server/auth.py
git_fork_recon_server/cache.py
git_fork_recon_server/cli.py
git_fork_recon_server/models.py
git_fork_recon_server/static/favicon.ico
git_fork_recon_server/static/index.html
git_fork_recon-0.1.5.dist-info/METADATA
git_fork_recon-0.1.5.dist-info/WHEEL
git_fork_recon-0.1.5.dist-info/entry_points.txt
git_fork_recon-0.1.5.dist-info/licenses/LICENSE
git_fork_recon-0.1.5.dist-info/RECORD
