Metadata-Version: 2.4
Name: git-fork-recon
Version: 0.1.5
Summary: Analyse the network of forked git repositories
Project-URL: Homepage, https://github.com/pansapiens/git-fork-recon
Project-URL: Repository, https://github.com/pansapiens/git-fork-recon
Author-email: Andrew Perry <ajperry@pansapiens.com>
License-Expression: Apache-2.0
License-File: LICENSE
Keywords: analysis,cli,developer tools,fork,git,github,llm
Classifier: Development Status :: 5 - Production/Stable
Classifier: Environment :: Console
Classifier: Intended Audience :: Developers
Classifier: License :: OSI Approved :: Apache Software License
Classifier: Operating System :: OS Independent
Classifier: Programming Language :: Python :: 3
Classifier: Programming Language :: Python :: 3.9
Classifier: Programming Language :: Python :: 3.10
Classifier: Programming Language :: Python :: 3.11
Classifier: Programming Language :: Python :: 3.12
Classifier: Topic :: Software Development :: Version Control
Classifier: Topic :: Utilities
Requires-Python: >=3.10
Requires-Dist: gitpython>=3.1.0
Requires-Dist: httpx>=0.28.0
Requires-Dist: jinja2>=3.1.0
Requires-Dist: openrouter>=0.1.1
Requires-Dist: platformdirs>=4.2.2
Requires-Dist: pydantic>=2.0.0
Requires-Dist: pygithub>=2.8.1
Requires-Dist: rich>=13.0.0
Requires-Dist: tenacity>=8.0.0
Requires-Dist: tiktoken>=0.8.0
Requires-Dist: tomli>=2.0.0; python_version < '3.11'
Requires-Dist: typer>=0.15.0
Provides-Extra: dev
Requires-Dist: black>=24.0.0; extra == 'dev'
Requires-Dist: mypy>=1.8.0; extra == 'dev'
Requires-Dist: pytest>=7.0.0; extra == 'dev'
Requires-Dist: ruff>=0.2.0; extra == 'dev'
Provides-Extra: mcp
Requires-Dist: fastmcp; extra == 'mcp'
Provides-Extra: server
Requires-Dist: fastapi>=0.104.0; extra == 'server'
Requires-Dist: uvicorn[standard]>=0.24.0; extra == 'server'
